htgettoken/__init__.py
htgettoken-2.2.data/scripts/htdecodetoken
htgettoken-2.2.data/scripts/htdestroytoken
htgettoken-2.2.data/scripts/httokensh
htgettoken-2.2.dist-info/licenses/COPYING
htgettoken-2.2.dist-info/METADATA
htgettoken-2.2.dist-info/WHEEL
htgettoken-2.2.dist-info/entry_points.txt
htgettoken-2.2.dist-info/top_level.txt
htgettoken-2.2.dist-info/RECORD
