Metadata-Version: 2.4
Name: htgettoken
Version: 2.2
Home-page: https://github.com/fermitools/htgettoken
Author: Dave Dykstra
Author-email: dwd@fnal.gov
License: BSD-3-Clause
Project-URL: Bug Tracker, https://github.com/fermitools/htgettoken/issues
Project-URL: Source Code, https://github.com/fermitools/htgettoken
Classifier: Development Status :: 4 - Beta
Classifier: Intended Audience :: Science/Research
Classifier: License :: OSI Approved :: BSD License
Classifier: Natural Language :: English
Classifier: Programming Language :: Python
Classifier: Programming Language :: Python :: 3.5
Classifier: Programming Language :: Python :: 3.6
Classifier: Programming Language :: Python :: 3.7
Classifier: Programming Language :: Python :: 3.8
Classifier: Programming Language :: Python :: 3.9
Classifier: Programming Language :: Python :: 3.10
Classifier: Programming Language :: Python :: 3.11
Requires-Python: >=3.5
License-File: COPYING
Requires-Dist: gssapi
Requires-Dist: paramiko
Requires-Dist: urllib3
Dynamic: license-file
